agent_orchestrator/__init__.py
agent_orchestrator/py.typed
agent_orchestrator/agents/claude_agent.py
agent_orchestrator/agents/factory.py
agent_orchestrator/agents/gemini_agent.py
agent_orchestrator/auth/__init__.py
agent_orchestrator/auth/login_manager.py
agent_orchestrator/cli/main.py
agent_orchestrator/config/advanced_config.py
agent_orchestrator/core/__init__.py
agent_orchestrator/core/backlog_executor.py
agent_orchestrator/core/engine.py
agent_orchestrator/core/orchestrator.py
agent_orchestrator/core/scheduler.py
agent_orchestrator/core/sprint_executor.py
agent_orchestrator/core/storage.py
agent_orchestrator/core/validator.py
agent_orchestrator/dashboard/status_dashboard.py
agent_orchestrator/integrations/__init__.py
agent_orchestrator/integrations/github_integration.py
agent_orchestrator/integrations/integration_manager.py
agent_orchestrator/integrations/jira_integration.py
agent_orchestrator/integrations/slack_integration.py
agent_orchestrator/models/__init__.py
agent_orchestrator/models/backlog.py
agent_orchestrator/models/sprint.py
agent_orchestrator/models/task.py
agent_orchestrator/models/user.py
agent_orchestrator/reporting/progress_reporter.py
agent_orchestrator/templates/project_templates.py
agent_orchestrator/utils/advanced_logger.py
agent_orchestrator/utils/logger.py
agent_orchestrator/utils/markdown_parser.py
agent_orchestrator-2.0.0.dist-info/licenses/LICENSE
agent_orchestrator-2.0.0.dist-info/METADATA
agent_orchestrator-2.0.0.dist-info/WHEEL
agent_orchestrator-2.0.0.dist-info/entry_points.txt
agent_orchestrator-2.0.0.dist-info/top_level.txt
agent_orchestrator-2.0.0.dist-info/RECORD
