Metadata-Version: 2.4
Name: agent-orchestrator
Version: 2.0.0
Summary: Orquestrador de Agentes de IA para Desenvolvimento de Software
Home-page: https://github.com/luhfilho/agent-orchestrator
Author: Agent Orchestrator Team
Author-email: Agent Orchestrator Team <team@agent-orchestrator.dev>
Maintainer-email: Agent Orchestrator Team <team@agent-orchestrator.dev>
License: MIT
Project-URL: Homepage, https://github.com/luhfilho/agent-orchestrator
Project-URL: Documentation, https://github.com/luhfilho/agent-orchestrator/blob/main/README.md
Project-URL: Repository, https://github.com/luhfilho/agent-orchestrator.git
Project-URL: Bug Tracker, https://github.com/luhfilho/agent-orchestrator/issues
Project-URL: Changelog, https://github.com/luhfilho/agent-orchestrator/blob/main/CHANGELOG.md
Keywords: ai,agents,orchestration,development,automation,claude,gemini,software-development,task-automation
Classifier: Development Status :: 4 - Beta
Classifier: Intended Audience :: Developers
Classifier: License :: OSI Approved :: MIT License
Classifier: Operating System :: OS Independent
Classifier: Programming Language :: Python :: 3
Classifier: Programming Language :: Python :: 3.10
Classifier: Programming Language :: Python :: 3.11
Classifier: Programming Language :: Python :: 3.12
Classifier: Topic :: Software Development :: Libraries :: Python Modules
Classifier: Topic :: Software Development :: Quality Assurance
Classifier: Topic :: Software Development :: Testing
Classifier: Topic :: Software Development :: Build Tools
Classifier: Topic :: Scientific/Engineering :: Artificial Intelligence
Requires-Python: >=3.10
License-File: LICENSE
Requires-Dist: rich>=13.0.0
Requires-Dist: click>=8.0.0
Requires-Dist: pydantic>=2.0.0
Requires-Dist: pyyaml>=6.0
Requires-Dist: watchdog>=3.0.0
Requires-Dist: aiohttp>=3.8.0
Provides-Extra: dev
Requires-Dist: pytest>=7.0.0; extra == "dev"
Requires-Dist: pytest-asyncio>=0.21.0; extra == "dev"
Requires-Dist: pytest-cov>=4.0.0; extra == "dev"
Requires-Dist: black>=23.0.0; extra == "dev"
Requires-Dist: flake8>=6.0.0; extra == "dev"
Requires-Dist: mypy>=1.0.0; extra == "dev"
Requires-Dist: pre-commit>=3.0.0; extra == "dev"
Requires-Dist: build>=0.10.0; extra == "dev"
Requires-Dist: twine>=4.0.2; extra == "dev"
Provides-Extra: docs
Requires-Dist: sphinx>=6.0.0; extra == "docs"
Requires-Dist: sphinx-rtd-theme>=1.2.0; extra == "docs"
Dynamic: author
Dynamic: home-page
Dynamic: license-file
Dynamic: requires-python
